{
    "url": "/adminapi/v1/bots/14000000000080",
    "object": "bot",
    "data": {
        "modifier": {
            "name": "sandhya",
            "id": "14000000000006"
        },
        "connector": {
            "owner": {
                "email_id": "sandhya.v+3@zohotest.com",
                "name": "sandhya",
                "id": "14000000000006"
            },
            "status": "enabled",
            "type": "flow"
        },
        "typing_delay": 2,
        "modified_time": "1655978080883",
        "image_fkey": "",
        "working_hours": [
            "during_business_hours",
            "during_non_business_hours"
        ],
        "permissions": "15",
        "enabled": true,
        "creator": {
            "name": "sandhya",
            "id": "14000000000006"
        },
        "source_type": "developed",
        "trigger_events": [],
        "deleted": false,
        "selected_audience_set": "1",
        "triggering_events": {
            "type": "none"
        },
        "audience_sets": {
            "1": {
                "audience": {
                    "type": 3,
                    "event": "0",
                    "value": [
                        [
                            "36",
                            "1",
                            "3",
                            "",
                            "",
                            "",
                            "",
                            ""
                        ]
                    ]
                },
                "title": "All Visitor"
            }
        },
        "id": "14000000000080",
        "description": "",
        "app_id": "14000000000058",
        "department_ids": [],
        "chat_inactivity_rules": {
            "enabled": false,
            "rules": {
                "1": {
                    "delay_mins": 1,
                    "message": {
                        "default": {
                            "replies": [
                                {
                                    "text": "Is there anything else I might help you with today"
                                }
                            ]
                        }
                    },
                    "action": "reply"
                },
                "2": {
                    "delay_mins": 5,
                    "message": {
                        "default": {
                            "replies": [
                                {
                                    "text": "Thanks for contacting us! If you have any other queries, please feel free to contact us at any time."
                                }
                            ]
                        }
                    },
                    "action": "end"
                }
            }
        },
        "handoff_enabled": true,
        "all_departments": true,
        "published": false,
        "created_time": "1655978026229",
        "stats": {
            "last_used_time_in_millis": "0",
            "total_chat_duration_in_millis": "0",
            "number_of_transfered_chats": "0",
            "number_of_chats": "0",
            "number_of_resolved_chats": "0"
        },
        "image_url": "",
        "handoff_configs": {
            "default": {
                "text": "Connect with a human?",
                "ack": "Yes"
            }
        },
        "name": "kk"
    }
}
